Ej8/Verilog simulation/src/counter.v
/*******************************************************************************
* SincCounter:                                                                 *
*    *Recibe:                                                                  *
*       - Clk: señal de clock                                                  *                         
*       - Reset: en 1 vuelve la cuenta a 0.                                    *
*       - Enable: en 1 habilita el contador, en 0 la salida conserva su valor. *
*    *Devuelve:                                                                *
*       - Out: arreglo de WIDTH bits que contienen el valor de la cuenta.      *
*    *Funcion: contador sincronico de WIDTH Bits                               *
********************************************************************************/

module SincCounter(out, clk, reset, enable);

  parameter WIDTH = 8;

  output [WIDTH-1 : 0] out;
  input            clk, reset, enable;

  reg [WIDTH-1 : 0]   out = 0;
  wire            clk, reset;


  always @(posedge clk)
    if(enable)
      out <= out + 1;

  always @reset
    if (reset)
      assign out = 0;
    else
      deassign out;

endmodule // counter

Ej8/Verilog simulation/src/clock_lib.v
`timescale 100ns / 100ns

/* MODULO DE CLOCKS CON DIFERENTES PARAMETROS */

/****************************************************
* Clock_t:                                          *
*    *Parametros:                                   *
*          T_ON: tiempo en el estado alto           *                         
*          T_OFF: tiempo en el estado bajo          *
*          FIRST: estado inicial del clock          *
*          T0: corrimiento inicial en el tiempo     *
*****************************************************/
module ClockT(clk);

parameter T_ON = 5e6,        // tiempo en alto 
          T_OFF = 5e6,       // tiempo en bajo
          FIRST = 0,        // estado inicial
          T0 = 0;            // el usuario puede modificar el tiempo en el que arranca

output reg clk; 

integer delay1 = 0, delay2 = 0, to=T0;

initial
    begin       //configura los delays dependiendo de cual sea el primer estado
        if(FIRST == 0)
            begin
                delay1 = T_OFF;
                delay2 = T_ON;
            end
        else
            begin
                delay1 = T_ON;
                delay2 = T_OFF;
            end    
        clk <= ~FIRST; 
    end

always
    begin: CLOCK_DRIVER
        begin
            if(to > 0)
                begin
                    #(to);
                    to = 0;
                end
            clk <= FIRST;  
            #(delay1);     
            clk <= ~FIRST;
            #(delay2);    
        end
    end  

endmodule

/****************************************************
* Clock_d:                                          *
*    *Parametros:                                   *
*          PERIOD: periodo en multiplos de ticks    *                         
*          FIRST: estado inicial del clock          *
*          DUTY CYCLE: t_on/t_off del clock, <1     *
*          T0: corrimiento inicial en el tiempo     *
*****************************************************/

module ClockD(clk);

parameter PERIOD = 10e6,     // periodo
          FIRST = 0,        // estado inicial
          DUTY = 0.5,       // duty cycle
          T0 = 0;           // el usuario de esta libreria puede modificar el tiempo en el que arranca

output wire clk;

ClockT #(               //arma el ClockT con los parametros que recibe
    .T_ON( PERIOD*DUTY ),
    .T_OFF( PERIOD*(1-DUTY) ),
    .FIRST(FIRST),
    .T0(T0)
)auxclock(clk);

endmodule


/*****************************************************
* Clock_p:                                           *
*    *Parametros:                                    *
*          PERIOD: periodo en multiplos de ticks     *                         
*          T_ON: tiempo en el estado alto, <= PERIOD *
*          FIRST: estado inicial del clock          *
*          T0: corrimiento inicial en el tiempo      *
*****************************************************/
module ClockP(clk);

parameter PERIOD = 10e6,     // periodo
          T_ON = PERIOD/2,   // tiempo en alto
          FIRST = 0,         // estado inicial
          T0 = 0;            // el usuario puede modificar el tiempo en el que arranca

output wire clk;

ClockT #(
    .T_ON(T_ON),
    .T_OFF(PERIOD - T_ON),
    .FIRST(FIRST),
    .T0(T0)
)auxclock(clk);

endmodule

Ej8/Verilog simulation/src/tests/nico/src/comparator.v
/***************************************************************
* Comparator:                                                  *
*    *Parametros:                                              *
*          PERIOD: Periodo de la señal                         *                          
*          T_STOP: Tiempo en el que debe bajar la señal.       *
*    *Funcion: Devuelve señal emulada del comparador analogico *
****************************************************************/

module Comparator(comp);

parameter PERIOD = 100e3,
          T_STOP = 1e3;      //tiempo en el que debe pasar a 0
    
output wire comp;

ClockP #( 
    .PERIOD(PERIOD), 
    .T_ON(2*T_STOP), 
    .FIRST(0), 
    .T0(T_STOP)
  ) comparator(comp);

endmodule

Ej8/Verilog simulation/src/tests/nico/src/main.v
`timescale 100us / 100ns

/*ARMAR COMPUERTAS REALES*/
/*ARMAR MULTIVIBRADORES IDEALES*/
/*ARMAR MULTIVIBRADORES REALES*/

// PRUEBA COUNTER Y SINCRONIZACION

module count_test;

  // My signal definitions
  wire clk1, clk2, comp;

  ClockD #( 
    .PERIOD(1e3) 
  ) clock1(clk1);  //clock del contador, 10kHz

  ClockD #( 
    .PERIOD(200e3) , 
    .FIRST(1) 
  ) clock2(clk2);     //clock con la frecuencia de la triangular(50Hz) resetea el contador, arranca en 1 (triangular en subida)

  Comparator #(
    .PERIOD(200e3),
    .T_STOP(60e3)
  ) compare(comp);    //simulacion de la salida del comparador de la triangular con el joystick

  wire[6:0] count;
  not(reset, clk2); //IMPLEMENTAR ACA UNA NOT REAL
  SincCounter #(.WIDTH(7)) my_counter (count, clk1, reset, comp);

  integer count_int;  //Para poder ver la cuenta en decimal en GTKWave
  always@(count)
    count_int = count;

  initial begin
    #800;  // cuenta hasta 100 o hasta que lo frenen
    $finish;
  end

  // Additional documentation on $dumpfile and $dumpvars: http://referencedesigner.com/tutorials/verilog/verilog_62.php
  // Setup to allow us to pass an output path for $dumpfile
  reg dummy;
  reg[8*64:0] dumpfile_path = "output.vcd";

  initial begin
    dummy = $value$plusargs("VCD_PATH=%s", dumpfile_path);
    $dumpfile(dumpfile_path);
    $dumpvars(0,count_test);
  end

endmodule   // End of count_test module 

/*  PRUEBA CLOCKS

module clocks_tests;

  // My signal definitions
  wire clkd, clkt, clkp;
  
  ClockD #(
    .PERIOD(3),
    .FIRST(1),  
    .DUTY(0.7),
    .T0(2)
  ) clock1(clkd);

  ClockT #( 
    .T_ON(4), 
    .T_OFF(5), 
    .FIRST(1), 
    .T0(6) 
  ) clock2(clkt);
  
  ClockP #( 
    .PERIOD(5), 
    .T_ON(4), 
    .FIRST(0), 
    .T0(0) 
  ) comparator(clkp);

  initial begin
    #100;
    $finish;    
  end

  reg dummy;
  reg[8*64:0] dumpfile_path = "output.vcd";

  initial begin
    dummy = $value$plusargs("VCD_PATH=%s", dumpfile_path);
    $dumpfile(dumpfile_path);
    $dumpvars(0,clocks_tests);
  end

endmodule // End of module clocks_tests */


//PRUEBA DELAYS

/*module hello_world;

  // My signal definitions
  reg signal;
  wire delayed;

  delay mydelay(signal, delayed);

  initial begin

    signal = 0;
    #1;
    signal = 1;
    #1;
    signal = 0;
    #1;
    $finish;

  end

  // Additional documentation on $dumpfile and $dumpvars: http://referencedesigner.com/tutorials/verilog/verilog_62.php
  // Setup to allow us to pass an output path for $dumpfile
  reg dummy;
  reg[8*64:0] dumpfile_path = "output.vcd";

  initial begin
    dummy = $value$plusargs("VCD_PATH=%s", dumpfile_path);
    $dumpfile(dumpfile_path);
    $dumpvars(0,hello_world);
  end

endmodule // End of Module hello_world
*/

Ej8/Verilog simulation/src/tests/nico/bin/output.vcd
$date
	Thu Oct 17 22:40:15 2019
$end
$version
	Icarus Verilog
$end
$timescale
	100ns
$end
$scope module count_test $end
$var wire 1 ! reset $end
$var wire 7 " count [6:0] $end
$var wire 1 # comp $end
$var wire 1 $ clk2 $end
$var wire 1 % clk1 $end
$var reg 1 & dummy $end
$var reg 513 ' dumpfile_path [512:0] $end
$var integer 32 ( count_int [31:0] $end
$scope module clock1 $end
$var wire 1 % clk $end
$scope module auxclock $end
$var reg 1 % clk $end
$var integer 32 ) delay1 [31:0] $end
$var integer 32 * delay2 [31:0] $end
$var integer 32 + to [31:0] $end
$scope begin CLOCK_DRIVER $end
$upscope $end
$upscope $end
$upscope $end
$scope module clock2 $end
$var wire 1 $ clk $end
$scope module auxclock $end
$var reg 1 $ clk $end
$var integer 32 , delay1 [31:0] $end
$var integer 32 - delay2 [31:0] $end
$var integer 32 . to [31:0] $end
$scope begin CLOCK_DRIVER $end
$upscope $end
$upscope $end
$upscope $end
$scope module compare $end
$var wire 1 # comp $end
$scope module comparator $end
$var wire 1 # clk $end
$scope module auxclock $end
$var reg 1 # clk $end
$var integer 32 / delay1 [31:0] $end
$var integer 32 0 delay2 [31:0] $end
$var integer 32 1 to [31:0] $end
$scope begin CLOCK_DRIVER $end
$upscope $end
$upscope $end
$upscope $end
$upscope $end
$scope module my_counter $end
$var wire 1 % clk $end
$var wire 1 # enable $end
$var wire 1 ! reset $end
$var reg 7 2 out [6:0] $end
$upscope $end
$upscope $end
$enddefinitions $end
#0
$dumpvars
b1 2
b1110101001100000 1
b11101010011000000 0
b10011100010000000 /
b0 .
b11000011010100000 -
b11000011010100000 ,
b0 +
b111110100 *
b111110100 )
b1 (
b1101111011101010111010001110000011101010111010000101110011101100110001101100100 '
0&
0%
1$
1#
b1 "
0!
$end
#500
b10 (
b10 "
b10 2
1%
#1000
0%
#1500
b11 (
b11 "
b11 2
1%
#2000
0%
#2500
b100 (
b100 "
b100 2
1%
#3000
0%
#3500
b101 (
b101 "
b101 2
1%
#4000
0%
#4500
b110 (
b110 "
b110 2
1%
#5000
0%
#5500
b111 (
b111 "
b111 2
1%
#6000
0%
#6500
b1000 (
b1000 "
b1000 2
1%
#7000
0%
#7500
b1001 (
b1001 "
b1001 2
1%
#8000
0%
#8500
b1010 (
b1010 "
b1010 2
1%
#9000
0%
#9500
b1011 (
b1011 "
b1011 2
1%
#10000
0%
#10500
b1100 (
b1100 "
b1100 2
1%
#11000
0%
#11500
b1101 (
b1101 "
b1101 2
1%
#12000
0%
#12500
b1110 (
b1110 "
b1110 2
1%
#13000
0%
#13500
b1111 (
b1111 "
b1111 2
1%
#14000
0%
#14500
b10000 (
b10000 "
b10000 2
1%
#15000
0%
#15500
b10001 (
b10001 "
b10001 2
1%
#16000
0%
#16500
b10010 (
b10010 "
b10010 2
1%
#17000
0%
#17500
b10011 (
b10011 "
b10011 2
1%
#18000
0%
#18500
b10100 (
b10100 "
b10100 2
1%
#19000
0%
#19500
b10101 (
b10101 "
b10101 2
1%
#20000
0%
#20500
b10110 (
b10110 "
b10110 2
1%
#21000
0%
#21500
b10111 (
b10111 "
b10111 2
1%
#22000
0%
#22500
b11000 (
b11000 "
b11000 2
1%
#23000
0%
#23500
b11001 (
b11001 "
b11001 2
1%
#24000
0%
#24500
b11010 (
b11010 "
b11010 2
1%
#25000
0%
#25500
b11011 (
b11011 "
b11011 2
1%
#26000
0%
#26500
b11100 (
b11100 "
b11100 2
1%
#27000
0%
#27500
b11101 (
b11101 "
b11101 2
1%
#28000
0%
#28500
b11110 (
b11110 "
b11110 2
1%
#29000
0%
#29500
b11111 (
b11111 "
b11111 2
1%
#30000
0%
#30500
b100000 (
b100000 "
b100000 2
1%
#31000
0%
#31500
b100001 (
b100001 "
b100001 2
1%
#32000
0%
#32500
b100010 (
b100010 "
b100010 2
1%
#33000
0%
#33500
b100011 (
b100011 "
b100011 2
1%
#34000
0%
#34500
b100100 (
b100100 "
b100100 2
1%
#35000
0%
#35500
b100101 (
b100101 "
b100101 2
1%
#36000
0%
#36500
b100110 (
b100110 "
b100110 2
1%
#37000
0%
#37500
b100111 (
b100111 "
b100111 2
1%
#38000
0%
#38500
b101000 (
b101000 "
b101000 2
1%
#39000
0%
#39500
b101001 (
b101001 "
b101001 2
1%
#40000
0%
#40500
b101010 (
b101010 "
b101010 2
1%
#41000
0%
#41500
b101011 (
b101011 "
b101011 2
1%
#42000
0%
#42500
b101100 (
b101100 "
b101100 2
1%
#43000
0%
#43500
b101101 (
b101101 "
b101101 2
1%
#44000
0%
#44500
b101110 (
b101110 "
b101110 2
1%
#45000
0%
#45500
b101111 (
b101111 "
b101111 2
1%
#46000
0%
#46500
b110000 (
b110000 "
b110000 2
1%
#47000
0%
#47500
b110001 (
b110001 "
b110001 2
1%
#48000
0%
#48500
b110010 (
b110010 "
b110010 2
1%
#49000
0%
#49500
b110011 (
b110011 "
b110011 2
1%
#50000
0%
#50500
b110100 (
b110100 "
b110100 2
1%
#51000
0%
#51500
b110101 (
b110101 "
b110101 2
1%
#52000
0%
#52500
b110110 (
b110110 "
b110110 2
1%
#53000
0%
#53500
b110111 (
b110111 "
b110111 2
1%
#54000
0%
#54500
b111000 (
b111000 "
b111000 2
1%
#55000
0%
#55500
b111001 (
b111001 "
b111001 2
1%
#56000
0%
#56500
b111010 (
b111010 "
b111010 2
1%
#57000
0%
#57500
b111011 (
b111011 "
b111011 2
1%
#58000
0%
#58500
b111100 (
b111100 "
b111100 2
1%
#59000
0%
#59500
b111101 (
b111101 "
b111101 2
1%
#60000
0%
0#
b0 1
